emailer/agent.py
volttron_emailer-0.1.0.dist-info/LICENSE
volttron_emailer-0.1.0.dist-info/METADATA
volttron_emailer-0.1.0.dist-info/WHEEL
volttron_emailer-0.1.0.dist-info/entry_points.txt
volttron_emailer-0.1.0.dist-info/RECORD
