Metadata-Version: 2.1
Name: volttron-emailer
Version: 0.1.0
Summary: 
Home-page: https://github.com/eclipse-volttron/volttron-emailer
License: Apache-2.0
Author: VOLTTRON Team
Author-email: volttron@pnnl.gov
Requires-Python: >=3.10,<4.0
Classifier: Intended Audience :: Developers
Classifier: Intended Audience :: Information Technology
Classifier: Intended Audience :: Other Audience
Classifier: Intended Audience :: Science/Research
Classifier: License :: OSI Approved :: Apache Software License
Classifier: Programming Language :: Python :: 3
Classifier: Programming Language :: Python :: 3.10
Classifier: Programming Language :: Python :: 3.11
Classifier: Programming Language :: Python :: 3.12
Classifier: Programming Language :: Python :: 3 :: Only
Requires-Dist: volttron (>=10.0.4rc1,<11.0.0)
Project-URL: Repository, https://github.com/eclipse-volttron/volttron-emailer
